{
  "applications": [
    {
      "id": "wrapsafe",
      "name": "Wrapsafe",
      "version": "4.0.3",
      "vendor": "NCR",
      "description": "Exclusive multimedia matrices",
      "categoryId": "core",
      "applicationSize": "Small",
      "status": "Standard",
      "condition": [
        { "label": "fy20q1", "value": "Average" },
        { "label": "fy20q2", "value": "Good" },
        { "label": "fy20q3", "value": "Average" }
      ],
      "sme_name": "Dorri Friatt",
      "vendor_phone": "+351 592 522 0677",
      "months_to_renew_support": 12,
      "hostedtype": "OnPremise1",
      "vendor_contact_name": "Shara Rangall",
      "support_cost": "75",
      "type": "OffShelf",
      "deployment_date": "28/5/15",
      "licensing_cost": "177",
      "end_of_life": "30/10/19",
      "rating": "good",
      "investment_24m": "737",
      "investment_number": 485,
      "sme_email": "Tadd.Teese@memento.net.au",
      "department": "Marketing",
      "vendor_email": "Shara.Rangall@NCR.com",
      "end_of_maintenance": "10/8/17",
      "integrations": [
        {
          "id": "int-097",
          "name": "INT-097",
          "version": "0.48",
          "description": "Morbi non quam nec dui luctus rutrum. Nulla tellus.",
          "payload": "Colour",
          "targetApplicationId": "veribet",
          "categoryId": "mft",
          "status": "Standard",
          "pattern": "Countent Based Router",
          "last_deployment_date": "6/7/17",
          "golive_date": "24/5/12",
          "datacentre": "Dandenong",
          "sme_name": "Matelda Nuss",
          "complexity": "Low",
          "department": "Integration",
          "logical_server": "A2A",
          "sme_email": "mnussf@memento.net.au"
        }
      ]
    }
  ]
}